Chainson-0.2.dist-info/DESCRIPTION.rst
Chainson-0.2.dist-info/METADATA
Chainson-0.2.dist-info/RECORD
Chainson-0.2.dist-info/WHEEL
Chainson-0.2.dist-info/metadata.json
Chainson-0.2.dist-info/top_level.txt
chainson/__init__.py
