Metadata-Version: 2.0
Name: Chainson
Version: 0.2
Summary: Chainable JSON Encoder
Home-page: UNKNOWN
Author: Shiqiao Du
Author-email: lucidfrontier.45@gmail.com
License: Apache License 2.0
Platform: UNKNOWN
Requires-Dist: six
Requires-Dist: future
